SimpleDump/SimpleDump.py
SimpleDump/__init__.py
SimpleDump-0.1.1.dist-info/LICENSE
SimpleDump-0.1.1.dist-info/METADATA
SimpleDump-0.1.1.dist-info/WHEEL
SimpleDump-0.1.1.dist-info/top_level.txt
SimpleDump-0.1.1.dist-info/RECORD
